galgopy/__init__.py
galgopy/ga.py
galgopy/utils.py
galgopy/crossover/__init__.py
galgopy/crossover/crossover.py
galgopy/crossover/functional.py
galgopy/mutation/__init__.py
galgopy/mutation/functional.py
galgopy/mutation/mutation.py
galgopy/selection/__init__.py
galgopy/selection/functional.py
galgopy/selection/selection.py
galgopy-0.1.1.dist-info/METADATA
galgopy-0.1.1.dist-info/WHEEL
galgopy-0.1.1.dist-info/licenses/LICENSE
galgopy-0.1.1.dist-info/RECORD
