Metadata-Version: 2.4
Name: galgopy
Version: 0.1.1
Summary: Basic implementation of a genetic algorithm (GA).
Project-URL: Homepage, https://github.com/vec2pt/galgopy
Project-URL: Repository, https://github.com/vec2pt/galgopy.git
Project-URL: Issues, https://github.com/vec2pt/galgopy/issues
Author: vec2pt
Maintainer: vec2pt
License-Expression: MIT
License-File: LICENSE
Keywords: algorithm,ga,genetic-algorithm,optimization
Classifier: Development Status :: 2 - Pre-Alpha
Classifier: Intended Audience :: Developers
Classifier: Intended Audience :: Science/Research
Classifier: License :: OSI Approved :: MIT License
Classifier: Operating System :: OS Independent
Classifier: Programming Language :: Python :: 3
Classifier: Programming Language :: Python :: 3.11
Classifier: Programming Language :: Python :: 3.12
Classifier: Programming Language :: Python :: 3.13
Classifier: Programming Language :: Python :: 3.14
Requires-Python: >=3.11
Requires-Dist: numpy
Provides-Extra: dev
Requires-Dist: ruff; extra == 'dev'
Provides-Extra: test
Requires-Dist: pytest; extra == 'test'
